pauvre/__init__.py
pauvre/bamparse.py
pauvre/browser.py
pauvre/custommargin.py
pauvre/functions.py
pauvre/gfftools.py
pauvre/marginplot.py
pauvre/pauvre_main.py
pauvre/rcparams.py
pauvre/redwood.py
pauvre/stats.py
pauvre/synplot.py
pauvre/version.py
pauvre/lsi/Q.py
pauvre/lsi/T.py
pauvre/lsi/__init__.py
pauvre/lsi/helper.py
pauvre/lsi/lsi.py
pauvre/lsi/test.py
pauvre/tests/__init__.py
pauvre/tests/test_synplot.py
pauvre-0.2.3.dist-info/METADATA
pauvre-0.2.3.dist-info/WHEEL
pauvre-0.2.3.dist-info/entry_points.txt
pauvre-0.2.3.dist-info/top_level.txt
pauvre-0.2.3.dist-info/RECORD
