Metadata-Version: 2.1
Name: pauvre
Version: 0.2.3
Summary: Tools for plotting Oxford Nanopore and other long-read data.
Home-page: https://github.com/conchoecia/pauvre
Author: Darrin Schultz
Author-email: dts@ucsc.edu
License: UNKNOWN
Platform: UNKNOWN
Classifier: Development Status :: 2 - Pre-Alpha
Classifier: License :: OSI Approved :: GNU General Public License v3 (GPLv3)
Classifier: Programming Language :: Python :: 3
Classifier: Programming Language :: Python :: 3.6
Classifier: Programming Language :: Python :: 3.7
Classifier: Operating System :: POSIX :: Linux
Classifier: Topic :: Scientific/Engineering :: Bio-Informatics
Classifier: Intended Audience :: Science/Research
Requires-Python: >=3
Requires-Dist: matplotlib (>=2.0.2)
Requires-Dist: biopython (>=1.68)
Requires-Dist: pandas (>=0.20.1)
Requires-Dist: numpy (>=1.12.1)
Requires-Dist: scipy
Requires-Dist: scikit-learn
